sy_test/__init__.py
sy_test/test.py
seoy_Test-0.1.dist-info/METADATA
seoy_Test-0.1.dist-info/WHEEL
seoy_Test-0.1.dist-info/top_level.txt
seoy_Test-0.1.dist-info/RECORD
